saltlint/__init__.py
saltlint/__main__.py
saltlint/cli.py
saltlint/config.py
saltlint/utils.py
saltlint/formatters/__init__.py
saltlint/formatters/base.py
saltlint/formatters/default.py
saltlint/formatters/json.py
saltlint/formatters/severity.py
saltlint/linter/__init__.py
saltlint/linter/collection.py
saltlint/linter/match.py
saltlint/linter/rule.py
saltlint/linter/runner.py
saltlint/rules/CmdRunQuietRule.py
saltlint/rules/CmdWaitRecommendRule.py
saltlint/rules/FileExtensionRule.py
saltlint/rules/FileModeLeadingZeroRule.py
saltlint/rules/FileModeQuotationRule.py
saltlint/rules/JinjaCommentHasSpacesRule.py
saltlint/rules/JinjaPillarGrainsGetFormatRule.py
saltlint/rules/JinjaStatementHasSpacesRule.py
saltlint/rules/JinjaVariableHasSpacesRule.py
saltlint/rules/LineTooLongRule.py
saltlint/rules/NestedDictRule.py
saltlint/rules/NoIrregularSpacesRule.py
saltlint/rules/NoTabsRule.py
saltlint/rules/SLSFileNameRule.py
saltlint/rules/StateDeprecationDockerAbsent.py
saltlint/rules/StateDeprecationDockerImageAbsent.py
saltlint/rules/StateDeprecationDockerImagePresent.py
saltlint/rules/StateDeprecationDockerModWatch.py
saltlint/rules/StateDeprecationDockerNetworkAbsent.py
saltlint/rules/StateDeprecationDockerNetworkPresent.py
saltlint/rules/StateDeprecationDockerRunning.py
saltlint/rules/StateDeprecationDockerStopped.py
saltlint/rules/StateDeprecationDockerVolumeAbsent.py
saltlint/rules/StateDeprecationDockerVolumePresent.py
saltlint/rules/StateDeprecationElasticsearchIndexRule.py
saltlint/rules/StateDeprecationVirtRevertedRule.py
saltlint/rules/StateDeprecationVirtSavedRule.py
saltlint/rules/StateDeprecationVirtUnpoweredRule.py
saltlint/rules/TrailingWhitespaceRule.py
saltlint/rules/TypoOnchangesRule.py
saltlint/rules/TypoRequireRule.py
saltlint/rules/YamlHasOctalValueRule.py
saltlint/rules/__init__.py
salt_lint-0.9.2.dist-info/LICENSE
salt_lint-0.9.2.dist-info/LICENSE.ansible-lint
salt_lint-0.9.2.dist-info/METADATA
salt_lint-0.9.2.dist-info/WHEEL
salt_lint-0.9.2.dist-info/entry_points.txt
salt_lint-0.9.2.dist-info/top_level.txt
salt_lint-0.9.2.dist-info/RECORD
